ddbsizemetric/__init__.py
ddbsizemetric/py.typed
ddbsizemetric/_jsii/__init__.py
ddbsizemetric/_jsii/ddbsizemetric@0.1.0-alpha.9.jsii.tgz
ddbsizemetric-0.1.0a9.dist-info/METADATA
ddbsizemetric-0.1.0a9.dist-info/WHEEL
ddbsizemetric-0.1.0a9.dist-info/top_level.txt
ddbsizemetric-0.1.0a9.dist-info/RECORD
